sqlbox/__init__.py
sqlbox/creat_db.py
sqlbox/exception_.py
sqlbox/sqlbox.py
sqlbox/table.py
sqlbox-0.0.1.dist-info/METADATA
sqlbox-0.0.1.dist-info/WHEEL
sqlbox-0.0.1.dist-info/top_level.txt
sqlbox-0.0.1.dist-info/RECORD
