Metadata-Version: 2.1
Name: sqlbox
Version: 0.0.1
Summary: sqlbox is a package written in Python that allows people who don't know how to write SQL to write databases and manage them
Home-page: https://github.com/Cjenf/sqlbox
Author: Cheng
Author-email: cjenf844747@gmail.com
Requires-Python: >=3.11.4
